{
    "AX(CDD)": {
        "error": 0.0,
        "error_type": "SEM",
        "filter_outliers_dict": {
            "filter_outliers": true,
            "iterations": 1,
            "std_devs": 2
        },
        "fit": "average",
        "modifier_error": 1.2996428394153575e-05,
        "modifier_value": 6.69471664253423e-05,
        "value": 0.0
    },
    "H1": {
        "error": 0.008078348071885776,
        "error_type": "SEM",
        "filter_outliers_dict": {
            "filter_outliers": true,
            "iterations": 1,
            "std_devs": 2
        },
        "fit": "average",
        "modifier_error": 0.0,
        "modifier_value": 0.0,
        "value": 0.30632396368388487
    },
    "H2": {
        "error": 0.014814900252075979,
        "error_type": "SEM",
        "filter_outliers_dict": {
            "filter_outliers": true,
            "iterations": 1,
            "std_devs": 2
        },
        "fit": "average",
        "modifier_error": 0.0,
        "modifier_value": 0.0,
        "value": 0.10872519231959059
    },
    "L1": {
        "error": 0.005291509945487838,
        "error_type": "SEM",
        "filter_outliers_dict": {
            "filter_outliers": true,
            "iterations": 1,
            "std_devs": 2
        },
        "fit": "average",
        "modifier_error": 0.0,
        "modifier_value": 0.0,
        "value": 0.11670991517231245
    },
    "L2(CDD)": {
        "error": 1.1027429696791495e-22,
        "error_type": "SEM",
        "filter_outliers_dict": {
            "filter_outliers": true,
            "iterations": 1,
            "std_devs": 10
        },
        "fit": "average",
        "modifier_error": 3.4385317462988895e-06,
        "modifier_value": 4.686301649773962e-06,
        "value": 4.686301649773961e-06
    }
}